ProxyParser.py
proxyparser_checker-1.0.0.dist-info/METADATA
proxyparser_checker-1.0.0.dist-info/WHEEL
proxyparser_checker-1.0.0.dist-info/RECORD
